[
  {
    "frame_id": 0,
    "description": "In the video, a young girl is seen performing a ballet routine on a living room floor.",
    "objects": [
      "floor",
      "ballet",
      "routine",
      "young",
      "girl",
      "room"
    ],
    "actions": [
      "living",
      "performing"
    ],
    "segment_id": 0
  },
  {
    "frame_id": 1,
    "description": "In the video, a young girl is seen performing a ballet routine on a living room floor.",
    "objects": [
      "floor",
      "ballet",
      "routine",
      "young",
      "girl",
      "room"
    ],
    "actions": [
      "living",
      "performing"
    ],
    "segment_id": 0
  },
  {
    "frame_id": 2,
    "description": "In the video, a young girl is seen performing a ballet routine on a living room floor.",
    "objects": [
      "floor",
      "ballet",
      "routine",
      "young",
      "girl",
      "room"
    ],
    "actions": [
      "living",
      "performing"
    ],
    "segment_id": 0
  },
  {
    "frame_id": 3,
    "description": "In the video, a young girl is seen performing a ballet routine on a living room floor.",
    "objects": [
      "floor",
      "ballet",
      "routine",
      "young",
      "girl",
      "room"
    ],
    "actions": [
      "living",
      "performing"
    ],
    "segment_id": 0
  },
  {
    "frame_id": 4,
    "description": "In the video, a young girl is seen performing a ballet routine on a living room floor.",
    "objects": [
      "floor",
      "ballet",
      "routine",
      "young",
      "girl",
      "room"
    ],
    "actions": [
      "living",
      "performing"
    ],
    "segment_id": 0
  },
  {
    "frame_id": 5,
    "description": "In the video, a young girl is seen performing a ballet routine on a living room floor.",
    "objects": [
      "floor",
      "ballet",
      "routine",
      "young",
      "girl",
      "room"
    ],
    "actions": [
      "living",
      "performing"
    ],
    "segment_id": 0
  },
  {
    "frame_id": 6,
    "description": "In the video, a young girl is seen performing a ballet routine on a living room floor.",
    "objects": [
      "floor",
      "ballet",
      "routine",
      "young",
      "girl",
      "room"
    ],
    "actions": [
      "living",
      "performing"
    ],
    "segment_id": 0
  },
  {
    "frame_id": 7,
    "description": "In the video, a young girl is seen performing a ballet routine on a living room floor.",
    "objects": [
      "floor",
      "ballet",
      "routine",
      "young",
      "girl",
      "room"
    ],
    "actions": [
      "living",
      "performing"
    ],
    "segment_id": 0
  },
  {
    "frame_id": 8,
    "description": "She is dressed in a black leotard and tights, with her arms outstretched and ballet shoes on.",
    "objects": [
      "ballet",
      "she",
      "arms",
      "leotard",
      "her",
      "black"
    ],
    "actions": [
      "outstretched",
      "shoes",
      "dressed",
      "tights"
    ],
    "segment_id": 1
  },
  {
    "frame_id": 9,
    "description": "She is dressed in a black leotard and tights, with her arms outstretched and ballet shoes on.",
    "objects": [
      "ballet",
      "she",
      "arms",
      "leotard",
      "her",
      "black"
    ],
    "actions": [
      "outstretched",
      "shoes",
      "dressed",
      "tights"
    ],
    "segment_id": 1
  },
  {
    "frame_id": 10,
    "description": "She is dressed in a black leotard and tights, with her arms outstretched and ballet shoes on.",
    "objects": [
      "ballet",
      "she",
      "arms",
      "leotard",
      "her",
      "black"
    ],
    "actions": [
      "outstretched",
      "shoes",
      "dressed",
      "tights"
    ],
    "segment_id": 1
  },
  {
    "frame_id": 11,
    "description": "She is dressed in a black leotard and tights, with her arms outstretched and ballet shoes on.",
    "objects": [
      "ballet",
      "she",
      "arms",
      "leotard",
      "her",
      "black"
    ],
    "actions": [
      "outstretched",
      "shoes",
      "dressed",
      "tights"
    ],
    "segment_id": 1
  },
  {
    "frame_id": 12,
    "description": "She is dressed in a black leotard and tights, with her arms outstretched and ballet shoes on.",
    "objects": [
      "ballet",
      "she",
      "arms",
      "leotard",
      "her",
      "black"
    ],
    "actions": [
      "outstretched",
      "shoes",
      "dressed",
      "tights"
    ],
    "segment_id": 1
  },
  {
    "frame_id": 13,
    "description": "She is dressed in a black leotard and tights, with her arms outstretched and ballet shoes on.",
    "objects": [
      "ballet",
      "she",
      "arms",
      "leotard",
      "her",
      "black"
    ],
    "actions": [
      "outstretched",
      "shoes",
      "dressed",
      "tights"
    ],
    "segment_id": 1
  },
  {
    "frame_id": 14,
    "description": "She is dressed in a black leotard and tights, with her arms outstretched and ballet shoes on.",
    "objects": [
      "ballet",
      "she",
      "arms",
      "leotard",
      "her",
      "black"
    ],
    "actions": [
      "outstretched",
      "shoes",
      "dressed",
      "tights"
    ],
    "segment_id": 1
  },
  {
    "frame_id": 15,
    "description": "She is dressed in a black leotard and tights, with her arms outstretched and ballet shoes on.",
    "objects": [
      "ballet",
      "she",
      "arms",
      "leotard",
      "her",
      "black"
    ],
    "actions": [
      "outstretched",
      "shoes",
      "dressed",
      "tights"
    ],
    "segment_id": 1
  },
  {
    "frame_id": 16,
    "description": "Her hair is in a ponytail and she is smiling as she performs.",
    "objects": [
      "hair",
      "ponytail",
      "she",
      "her"
    ],
    "actions": [
      "smiling",
      "performs"
    ],
    "segment_id": 2
  },
  {
    "frame_id": 17,
    "description": "Her hair is in a ponytail and she is smiling as she performs.",
    "objects": [
      "hair",
      "ponytail",
      "she",
      "her"
    ],
    "actions": [
      "smiling",
      "performs"
    ],
    "segment_id": 2
  },
  {
    "frame_id": 18,
    "description": "Her hair is in a ponytail and she is smiling as she performs.",
    "objects": [
      "hair",
      "ponytail",
      "she",
      "her"
    ],
    "actions": [
      "smiling",
      "performs"
    ],
    "segment_id": 2
  },
  {
    "frame_id": 19,
    "description": "Her hair is in a ponytail and she is smiling as she performs.",
    "objects": [
      "hair",
      "ponytail",
      "she",
      "her"
    ],
    "actions": [
      "smiling",
      "performs"
    ],
    "segment_id": 2
  },
  {
    "frame_id": 20,
    "description": "Her hair is in a ponytail and she is smiling as she performs.",
    "objects": [
      "hair",
      "ponytail",
      "she",
      "her"
    ],
    "actions": [
      "smiling",
      "performs"
    ],
    "segment_id": 2
  },
  {
    "frame_id": 21,
    "description": "Her hair is in a ponytail and she is smiling as she performs.",
    "objects": [
      "hair",
      "ponytail",
      "she",
      "her"
    ],
    "actions": [
      "smiling",
      "performs"
    ],
    "segment_id": 2
  },
  {
    "frame_id": 22,
    "description": "Her hair is in a ponytail and she is smiling as she performs.",
    "objects": [
      "hair",
      "ponytail",
      "she",
      "her"
    ],
    "actions": [
      "smiling",
      "performs"
    ],
    "segment_id": 2
  },
  {
    "frame_id": 23,
    "description": "Her hair is in a ponytail and she is smiling as she performs.",
    "objects": [
      "hair",
      "ponytail",
      "she",
      "her"
    ],
    "actions": [
      "smiling",
      "performs"
    ],
    "segment_id": 2
  },
  {
    "frame_id": 24,
    "description": "She finishes her routine by striking a pose with her hands outstretched and smiling.",
    "objects": [
      "she",
      "pose",
      "routine",
      "her"
    ],
    "actions": [
      "striking",
      "hands",
      "outstretched",
      "finishes"
    ],
    "segment_id": 3
  },
  {
    "frame_id": 25,
    "description": "She finishes her routine by striking a pose with her hands outstretched and smiling.",
    "objects": [
      "she",
      "pose",
      "routine",
      "her"
    ],
    "actions": [
      "striking",
      "hands",
      "outstretched",
      "finishes"
    ],
    "segment_id": 3
  },
  {
    "frame_id": 26,
    "description": "She finishes her routine by striking a pose with her hands outstretched and smiling.",
    "objects": [
      "she",
      "pose",
      "routine",
      "her"
    ],
    "actions": [
      "striking",
      "hands",
      "outstretched",
      "finishes"
    ],
    "segment_id": 3
  },
  {
    "frame_id": 27,
    "description": "She finishes her routine by striking a pose with her hands outstretched and smiling.",
    "objects": [
      "she",
      "pose",
      "routine",
      "her"
    ],
    "actions": [
      "striking",
      "hands",
      "outstretched",
      "finishes"
    ],
    "segment_id": 3
  },
  {
    "frame_id": 28,
    "description": "She finishes her routine by striking a pose with her hands outstretched and smiling.",
    "objects": [
      "she",
      "pose",
      "routine",
      "her"
    ],
    "actions": [
      "striking",
      "hands",
      "outstretched",
      "finishes"
    ],
    "segment_id": 3
  },
  {
    "frame_id": 29,
    "description": "She finishes her routine by striking a pose with her hands outstretched and smiling.",
    "objects": [
      "she",
      "pose",
      "routine",
      "her"
    ],
    "actions": [
      "striking",
      "hands",
      "outstretched",
      "finishes"
    ],
    "segment_id": 3
  },
  {
    "frame_id": 30,
    "description": "She finishes her routine by striking a pose with her hands outstretched and smiling.",
    "objects": [
      "she",
      "pose",
      "routine",
      "her"
    ],
    "actions": [
      "striking",
      "hands",
      "outstretched",
      "finishes"
    ],
    "segment_id": 3
  },
  {
    "frame_id": 31,
    "description": "She finishes her routine by striking a pose with her hands outstretched and smiling.",
    "objects": [
      "she",
      "pose",
      "routine",
      "her"
    ],
    "actions": [
      "striking",
      "hands",
      "outstretched",
      "finishes"
    ],
    "segment_id": 3
  }
]