[
  {
    "frame_id": 0,
    "description": "In this video, a woman is seen sitting on the ground with a black chicken by her side.",
    "objects": [
      "woman",
      "black",
      "her",
      "side",
      "ground",
      "this",
      "chicken"
    ],
    "actions": [
      "sitting"
    ],
    "segment_id": 0
  },
  {
    "frame_id": 1,
    "description": "In this video, a woman is seen sitting on the ground with a black chicken by her side.",
    "objects": [
      "woman",
      "black",
      "her",
      "side",
      "ground",
      "this",
      "chicken"
    ],
    "actions": [
      "sitting"
    ],
    "segment_id": 0
  },
  {
    "frame_id": 2,
    "description": "In this video, a woman is seen sitting on the ground with a black chicken by her side.",
    "objects": [
      "woman",
      "black",
      "her",
      "side",
      "ground",
      "this",
      "chicken"
    ],
    "actions": [
      "sitting"
    ],
    "segment_id": 0
  },
  {
    "frame_id": 3,
    "description": "In this video, a woman is seen sitting on the ground with a black chicken by her side.",
    "objects": [
      "woman",
      "black",
      "her",
      "side",
      "ground",
      "this",
      "chicken"
    ],
    "actions": [
      "sitting"
    ],
    "segment_id": 0
  },
  {
    "frame_id": 4,
    "description": "In this video, a woman is seen sitting on the ground with a black chicken by her side.",
    "objects": [
      "woman",
      "black",
      "her",
      "side",
      "ground",
      "this",
      "chicken"
    ],
    "actions": [
      "sitting"
    ],
    "segment_id": 0
  },
  {
    "frame_id": 5,
    "description": "In this video, a woman is seen sitting on the ground with a black chicken by her side.",
    "objects": [
      "woman",
      "black",
      "her",
      "side",
      "ground",
      "this",
      "chicken"
    ],
    "actions": [
      "sitting"
    ],
    "segment_id": 0
  },
  {
    "frame_id": 6,
    "description": "She is wearing a vibrant orange shirt and purple pants.",
    "objects": [
      "she",
      "orange",
      "vibrant",
      "shirt",
      "purple"
    ],
    "actions": [
      "wearing",
      "pants"
    ],
    "segment_id": 1
  },
  {
    "frame_id": 7,
    "description": "She is wearing a vibrant orange shirt and purple pants.",
    "objects": [
      "she",
      "orange",
      "vibrant",
      "shirt",
      "purple"
    ],
    "actions": [
      "wearing",
      "pants"
    ],
    "segment_id": 1
  },
  {
    "frame_id": 8,
    "description": "She is wearing a vibrant orange shirt and purple pants.",
    "objects": [
      "she",
      "orange",
      "vibrant",
      "shirt",
      "purple"
    ],
    "actions": [
      "wearing",
      "pants"
    ],
    "segment_id": 1
  },
  {
    "frame_id": 9,
    "description": "She is wearing a vibrant orange shirt and purple pants.",
    "objects": [
      "she",
      "orange",
      "vibrant",
      "shirt",
      "purple"
    ],
    "actions": [
      "wearing",
      "pants"
    ],
    "segment_id": 1
  },
  {
    "frame_id": 10,
    "description": "She is wearing a vibrant orange shirt and purple pants.",
    "objects": [
      "she",
      "orange",
      "vibrant",
      "shirt",
      "purple"
    ],
    "actions": [
      "wearing",
      "pants"
    ],
    "segment_id": 1
  },
  {
    "frame_id": 11,
    "description": "She is wearing a vibrant orange shirt and purple pants.",
    "objects": [
      "she",
      "orange",
      "vibrant",
      "shirt",
      "purple"
    ],
    "actions": [
      "wearing",
      "pants"
    ],
    "segment_id": 1
  },
  {
    "frame_id": 12,
    "description": "The woman is holding a blue object in her hand, which could be a toy, a small plushie, or a bag.",
    "objects": [
      "small",
      "woman",
      "blue",
      "bag",
      "her",
      "which",
      "plushie",
      "object"
    ],
    "actions": [
      "holding"
    ],
    "segment_id": 2
  },
  {
    "frame_id": 13,
    "description": "The woman is holding a blue object in her hand, which could be a toy, a small plushie, or a bag.",
    "objects": [
      "small",
      "woman",
      "blue",
      "bag",
      "her",
      "which",
      "plushie",
      "object"
    ],
    "actions": [
      "holding"
    ],
    "segment_id": 2
  },
  {
    "frame_id": 14,
    "description": "The woman is holding a blue object in her hand, which could be a toy, a small plushie, or a bag.",
    "objects": [
      "small",
      "woman",
      "blue",
      "bag",
      "her",
      "which",
      "plushie",
      "object"
    ],
    "actions": [
      "holding"
    ],
    "segment_id": 2
  },
  {
    "frame_id": 15,
    "description": "The woman is holding a blue object in her hand, which could be a toy, a small plushie, or a bag.",
    "objects": [
      "small",
      "woman",
      "blue",
      "bag",
      "her",
      "which",
      "plushie",
      "object"
    ],
    "actions": [
      "holding"
    ],
    "segment_id": 2
  },
  {
    "frame_id": 16,
    "description": "The woman is holding a blue object in her hand, which could be a toy, a small plushie, or a bag.",
    "objects": [
      "small",
      "woman",
      "blue",
      "bag",
      "her",
      "which",
      "plushie",
      "object"
    ],
    "actions": [
      "holding"
    ],
    "segment_id": 2
  },
  {
    "frame_id": 17,
    "description": "The woman is holding a blue object in her hand, which could be a toy, a small plushie, or a bag.",
    "objects": [
      "small",
      "woman",
      "blue",
      "bag",
      "her",
      "which",
      "plushie",
      "object"
    ],
    "actions": [
      "holding"
    ],
    "segment_id": 2
  },
  {
    "frame_id": 18,
    "description": "She appears to be in a playful and relaxed mood, as she interacts with the chicken by gently petting its neck.",
    "objects": [
      "its",
      "she",
      "neck",
      "mood",
      "gently",
      "playful",
      "chicken"
    ],
    "actions": [
      "petting",
      "interacts",
      "relaxed"
    ],
    "segment_id": 3
  },
  {
    "frame_id": 19,
    "description": "She appears to be in a playful and relaxed mood, as she interacts with the chicken by gently petting its neck.",
    "objects": [
      "its",
      "she",
      "neck",
      "mood",
      "gently",
      "playful",
      "chicken"
    ],
    "actions": [
      "petting",
      "interacts",
      "relaxed"
    ],
    "segment_id": 3
  },
  {
    "frame_id": 20,
    "description": "She appears to be in a playful and relaxed mood, as she interacts with the chicken by gently petting its neck.",
    "objects": [
      "its",
      "she",
      "neck",
      "mood",
      "gently",
      "playful",
      "chicken"
    ],
    "actions": [
      "petting",
      "interacts",
      "relaxed"
    ],
    "segment_id": 3
  },
  {
    "frame_id": 21,
    "description": "She appears to be in a playful and relaxed mood, as she interacts with the chicken by gently petting its neck.",
    "objects": [
      "its",
      "she",
      "neck",
      "mood",
      "gently",
      "playful",
      "chicken"
    ],
    "actions": [
      "petting",
      "interacts",
      "relaxed"
    ],
    "segment_id": 3
  },
  {
    "frame_id": 22,
    "description": "She appears to be in a playful and relaxed mood, as she interacts with the chicken by gently petting its neck.",
    "objects": [
      "its",
      "she",
      "neck",
      "mood",
      "gently",
      "playful",
      "chicken"
    ],
    "actions": [
      "petting",
      "interacts",
      "relaxed"
    ],
    "segment_id": 3
  },
  {
    "frame_id": 23,
    "description": "She appears to be in a playful and relaxed mood, as she interacts with the chicken by gently petting its neck.",
    "objects": [
      "its",
      "she",
      "neck",
      "mood",
      "gently",
      "playful",
      "chicken"
    ],
    "actions": [
      "petting",
      "interacts",
      "relaxed"
    ],
    "segment_id": 3
  },
  {
    "frame_id": 24,
    "description": "The chicken seems calm and content in her company, as it stands still while she pets it.",
    "objects": [
      "content",
      "she",
      "while",
      "pets",
      "calm",
      "her",
      "company",
      "still"
    ],
    "actions": [
      "seems",
      "stands"
    ],
    "segment_id": 4
  },
  {
    "frame_id": 25,
    "description": "The chicken seems calm and content in her company, as it stands still while she pets it.",
    "objects": [
      "content",
      "she",
      "while",
      "pets",
      "calm",
      "her",
      "company",
      "still"
    ],
    "actions": [
      "seems",
      "stands"
    ],
    "segment_id": 4
  },
  {
    "frame_id": 26,
    "description": "The chicken seems calm and content in her company, as it stands still while she pets it.",
    "objects": [
      "content",
      "she",
      "while",
      "pets",
      "calm",
      "her",
      "company",
      "still"
    ],
    "actions": [
      "seems",
      "stands"
    ],
    "segment_id": 4
  },
  {
    "frame_id": 27,
    "description": "The chicken seems calm and content in her company, as it stands still while she pets it.",
    "objects": [
      "content",
      "she",
      "while",
      "pets",
      "calm",
      "her",
      "company",
      "still"
    ],
    "actions": [
      "seems",
      "stands"
    ],
    "segment_id": 4
  },
  {
    "frame_id": 28,
    "description": "The chicken seems calm and content in her company, as it stands still while she pets it.",
    "objects": [
      "content",
      "she",
      "while",
      "pets",
      "calm",
      "her",
      "company",
      "still"
    ],
    "actions": [
      "seems",
      "stands"
    ],
    "segment_id": 4
  },
  {
    "frame_id": 29,
    "description": "The chicken seems calm and content in her company, as it stands still while she pets it.",
    "objects": [
      "content",
      "she",
      "while",
      "pets",
      "calm",
      "her",
      "company",
      "still"
    ],
    "actions": [
      "seems",
      "stands"
    ],
    "segment_id": 4
  },
  {
    "frame_id": 30,
    "description": "The scene is set in a garden or backyard, surrounded by lush greenery and vibrant flowers, creating a serene and peaceful atmosphere.",
    "objects": [
      "greenery",
      "serene",
      "vibrant",
      "lush",
      "peaceful",
      "garden",
      "backyard",
      "set"
    ],
    "actions": [
      "flowers",
      "surrounded",
      "creating"
    ],
    "segment_id": 5
  },
  {
    "frame_id": 31,
    "description": "The scene is set in a garden or backyard, surrounded by lush greenery and vibrant flowers, creating a serene and peaceful atmosphere.",
    "objects": [
      "greenery",
      "serene",
      "vibrant",
      "lush",
      "peaceful",
      "garden",
      "backyard",
      "set"
    ],
    "actions": [
      "flowers",
      "surrounded",
      "creating"
    ],
    "segment_id": 5
  }
]