[
  {
    "frame_id": 0,
    "description": "In this video, a group of young adults is seen inside a room, creating a lively and energetic atmosphere.",
    "objects": [
      "inside",
      "this",
      "lively",
      "energetic",
      "atmosphere",
      "group",
      "young",
      "room"
    ],
    "actions": [
      "adults",
      "creating"
    ],
    "segment_id": 0
  },
  {
    "frame_id": 1,
    "description": "In this video, a group of young adults is seen inside a room, creating a lively and energetic atmosphere.",
    "objects": [
      "inside",
      "this",
      "lively",
      "energetic",
      "atmosphere",
      "group",
      "young",
      "room"
    ],
    "actions": [
      "adults",
      "creating"
    ],
    "segment_id": 0
  },
  {
    "frame_id": 2,
    "description": "In this video, a group of young adults is seen inside a room, creating a lively and energetic atmosphere.",
    "objects": [
      "inside",
      "this",
      "lively",
      "energetic",
      "atmosphere",
      "group",
      "young",
      "room"
    ],
    "actions": [
      "adults",
      "creating"
    ],
    "segment_id": 0
  },
  {
    "frame_id": 3,
    "description": "The camera pans around, revealing a group of people sitting and standing, all of them dressed in casual attire.",
    "objects": [
      "casual",
      "people",
      "all",
      "pans",
      "them",
      "group",
      "attire",
      "around"
    ],
    "actions": [
      "standing",
      "dressed",
      "revealing",
      "sitting"
    ],
    "segment_id": 1
  },
  {
    "frame_id": 4,
    "description": "The camera pans around, revealing a group of people sitting and standing, all of them dressed in casual attire.",
    "objects": [
      "casual",
      "people",
      "all",
      "pans",
      "them",
      "group",
      "attire",
      "around"
    ],
    "actions": [
      "standing",
      "dressed",
      "revealing",
      "sitting"
    ],
    "segment_id": 1
  },
  {
    "frame_id": 5,
    "description": "The camera pans around, revealing a group of people sitting and standing, all of them dressed in casual attire.",
    "objects": [
      "casual",
      "people",
      "all",
      "pans",
      "them",
      "group",
      "attire",
      "around"
    ],
    "actions": [
      "standing",
      "dressed",
      "revealing",
      "sitting"
    ],
    "segment_id": 1
  },
  {
    "frame_id": 6,
    "description": "One of the individuals is holding a camera, capturing the moment, while others are engaged in conversation, adding to the dynamic nature of the scene.",
    "objects": [
      "while",
      "one",
      "conversation",
      "dynamic",
      "moment",
      "nature"
    ],
    "actions": [
      "holding",
      "capturing",
      "engaged",
      "adding"
    ],
    "segment_id": 2
  },
  {
    "frame_id": 7,
    "description": "One of the individuals is holding a camera, capturing the moment, while others are engaged in conversation, adding to the dynamic nature of the scene.",
    "objects": [
      "while",
      "one",
      "conversation",
      "dynamic",
      "moment",
      "nature"
    ],
    "actions": [
      "holding",
      "capturing",
      "engaged",
      "adding"
    ],
    "segment_id": 2
  },
  {
    "frame_id": 8,
    "description": "One of the individuals is holding a camera, capturing the moment, while others are engaged in conversation, adding to the dynamic nature of the scene.",
    "objects": [
      "while",
      "one",
      "conversation",
      "dynamic",
      "moment",
      "nature"
    ],
    "actions": [
      "holding",
      "capturing",
      "engaged",
      "adding"
    ],
    "segment_id": 2
  },
  {
    "frame_id": 9,
    "description": "The camera then focuses on a man who is laughing heartily, possibly sharing a joke or an amusing moment with his friends.",
    "objects": [
      "his",
      "man",
      "heartily",
      "joke",
      "who",
      "then",
      "moment",
      "possibly"
    ],
    "actions": [
      "friends",
      "sharing",
      "laughing",
      "focuses"
    ],
    "segment_id": 3
  },
  {
    "frame_id": 10,
    "description": "The camera then focuses on a man who is laughing heartily, possibly sharing a joke or an amusing moment with his friends.",
    "objects": [
      "his",
      "man",
      "heartily",
      "joke",
      "who",
      "then",
      "moment",
      "possibly"
    ],
    "actions": [
      "friends",
      "sharing",
      "laughing",
      "focuses"
    ],
    "segment_id": 3
  },
  {
    "frame_id": 11,
    "description": "The camera then focuses on a man who is laughing heartily, possibly sharing a joke or an amusing moment with his friends.",
    "objects": [
      "his",
      "man",
      "heartily",
      "joke",
      "who",
      "then",
      "moment",
      "possibly"
    ],
    "actions": [
      "friends",
      "sharing",
      "laughing",
      "focuses"
    ],
    "segment_id": 3
  },
  {
    "frame_id": 12,
    "description": "He is wearing a blue shirt and glasses.",
    "objects": [
      "blue",
      "shirt"
    ],
    "actions": [
      "wearing",
      "glasses"
    ],
    "segment_id": 4
  },
  {
    "frame_id": 13,
    "description": "He is wearing a blue shirt and glasses.",
    "objects": [
      "blue",
      "shirt"
    ],
    "actions": [
      "wearing",
      "glasses"
    ],
    "segment_id": 4
  },
  {
    "frame_id": 14,
    "description": "He is wearing a blue shirt and glasses.",
    "objects": [
      "blue",
      "shirt"
    ],
    "actions": [
      "wearing",
      "glasses"
    ],
    "segment_id": 4
  },
  {
    "frame_id": 15,
    "description": "Meanwhile, a woman in a black dress is seen in the background, contributing to the overall ambiance of the room.",
    "objects": [
      "woman",
      "ambiance",
      "dress",
      "meanwhile",
      "room",
      "overall",
      "black"
    ],
    "actions": [
      "contributing"
    ],
    "segment_id": 5
  },
  {
    "frame_id": 16,
    "description": "Meanwhile, a woman in a black dress is seen in the background, contributing to the overall ambiance of the room.",
    "objects": [
      "woman",
      "ambiance",
      "dress",
      "meanwhile",
      "room",
      "overall",
      "black"
    ],
    "actions": [
      "contributing"
    ],
    "segment_id": 5
  },
  {
    "frame_id": 17,
    "description": "Meanwhile, a woman in a black dress is seen in the background, contributing to the overall ambiance of the room.",
    "objects": [
      "woman",
      "ambiance",
      "dress",
      "meanwhile",
      "room",
      "overall",
      "black"
    ],
    "actions": [
      "contributing"
    ],
    "segment_id": 5
  },
  {
    "frame_id": 18,
    "description": "The room is filled with various objects that suggest a lived-in space.",
    "objects": [
      "suggest",
      "space",
      "that",
      "room"
    ],
    "actions": [
      "objects",
      "filled"
    ],
    "segment_id": 6
  },
  {
    "frame_id": 19,
    "description": "The room is filled with various objects that suggest a lived-in space.",
    "objects": [
      "suggest",
      "space",
      "that",
      "room"
    ],
    "actions": [
      "objects",
      "filled"
    ],
    "segment_id": 6
  },
  {
    "frame_id": 20,
    "description": "The room is filled with various objects that suggest a lived-in space.",
    "objects": [
      "suggest",
      "space",
      "that",
      "room"
    ],
    "actions": [
      "objects",
      "filled"
    ],
    "segment_id": 6
  },
  {
    "frame_id": 21,
    "description": "There's a bed in the background, perhaps indicating a bedroom setting, and a TV is present in the room, possibly displaying some form of entertainment.",
    "objects": [
      "present",
      "some",
      "bedroom",
      "entertainment",
      "possibly",
      "form",
      "room"
    ],
    "actions": [
      "there's",
      "indicating",
      "bed",
      "perhaps"
    ],
    "segment_id": 7
  },
  {
    "frame_id": 22,
    "description": "There's a bed in the background, perhaps indicating a bedroom setting, and a TV is present in the room, possibly displaying some form of entertainment.",
    "objects": [
      "present",
      "some",
      "bedroom",
      "entertainment",
      "possibly",
      "form",
      "room"
    ],
    "actions": [
      "there's",
      "indicating",
      "bed",
      "perhaps"
    ],
    "segment_id": 7
  },
  {
    "frame_id": 23,
    "description": "There's a bed in the background, perhaps indicating a bedroom setting, and a TV is present in the room, possibly displaying some form of entertainment.",
    "objects": [
      "present",
      "some",
      "bedroom",
      "entertainment",
      "possibly",
      "form",
      "room"
    ],
    "actions": [
      "there's",
      "indicating",
      "bed",
      "perhaps"
    ],
    "segment_id": 7
  },
  {
    "frame_id": 24,
    "description": "The people in the room seem to be enjoying each other's company, creating a sense of camaraderie and fun.",
    "objects": [
      "company",
      "each",
      "people",
      "sense",
      "fun",
      "seem",
      "camaraderie",
      "room"
    ],
    "actions": [
      "enjoying",
      "other's",
      "creating"
    ],
    "segment_id": 8
  },
  {
    "frame_id": 25,
    "description": "The people in the room seem to be enjoying each other's company, creating a sense of camaraderie and fun.",
    "objects": [
      "company",
      "each",
      "people",
      "sense",
      "fun",
      "seem",
      "camaraderie",
      "room"
    ],
    "actions": [
      "enjoying",
      "other's",
      "creating"
    ],
    "segment_id": 8
  },
  {
    "frame_id": 26,
    "description": "The people in the room seem to be enjoying each other's company, creating a sense of camaraderie and fun.",
    "objects": [
      "company",
      "each",
      "people",
      "sense",
      "fun",
      "seem",
      "camaraderie",
      "room"
    ],
    "actions": [
      "enjoying",
      "other's",
      "creating"
    ],
    "segment_id": 8
  },
  {
    "frame_id": 27,
    "description": "The camera then pans back to the man in the blue shirt, who is still laughing, indicating a joyful and lighthearted moment among the group.",
    "objects": [
      "still",
      "among",
      "man",
      "pans",
      "who",
      "blue",
      "then",
      "group"
    ],
    "actions": [
      "indicating",
      "lighthearted",
      "laughing"
    ],
    "segment_id": 9
  },
  {
    "frame_id": 28,
    "description": "The camera then pans back to the man in the blue shirt, who is still laughing, indicating a joyful and lighthearted moment among the group.",
    "objects": [
      "still",
      "among",
      "man",
      "pans",
      "who",
      "blue",
      "then",
      "group"
    ],
    "actions": [
      "indicating",
      "lighthearted",
      "laughing"
    ],
    "segment_id": 9
  },
  {
    "frame_id": 29,
    "description": "The camera then pans back to the man in the blue shirt, who is still laughing, indicating a joyful and lighthearted moment among the group.",
    "objects": [
      "still",
      "among",
      "man",
      "pans",
      "who",
      "blue",
      "then",
      "group"
    ],
    "actions": [
      "indicating",
      "lighthearted",
      "laughing"
    ],
    "segment_id": 9
  },
  {
    "frame_id": 30,
    "description": "The scene is full of energy and camaraderie, with everyone engaged in the moment.",
    "objects": [
      "full",
      "everyone",
      "moment",
      "energy",
      "camaraderie"
    ],
    "actions": [
      "engaged"
    ],
    "segment_id": 10
  },
  {
    "frame_id": 31,
    "description": "The scene is full of energy and camaraderie, with everyone engaged in the moment.",
    "objects": [
      "full",
      "everyone",
      "moment",
      "energy",
      "camaraderie"
    ],
    "actions": [
      "engaged"
    ],
    "segment_id": 10
  }
]